mcutil/__init__.py
mcutil/printer.py
mcutil-1.0.1.dist-info/LICENSE
mcutil-1.0.1.dist-info/METADATA
mcutil-1.0.1.dist-info/WHEEL
mcutil-1.0.1.dist-info/top_level.txt
mcutil-1.0.1.dist-info/RECORD
