Metadata-Version: 2.1
Name: mcutil
Version: 1.0.1
Summary: Some simple utilities for Python
Home-page: https://github.com/cuongpiger/mcutil
Author: Cuong. Duong Manh
Author-email: cuongdm8499@gmail.com
License: Apache License 2.0
Classifier: Development Status :: 5 - Production/Stable
Classifier: Intended Audience :: Developers
Classifier: License :: OSI Approved :: Apache Software License
Classifier: Natural Language :: English
Classifier: Programming Language :: Python :: 3.6
Classifier: Programming Language :: Python :: 3.7
Classifier: Programming Language :: Python :: 3.8
Classifier: Programming Language :: Python :: 3.9
Requires-Python: >=3.6
License-File: LICENSE
